{"type":"PR","pr":{"number":45,"head":"089a839058a29c27c94733d8cd8e2bbe4b51d5b3"},"user":"marcin.kowrygo","status":"draft","branch":"cms/80-000-hours-podcasts","collection":"templates_and_materials","title":"80,000 Hours podcasts","description":"A show about the world's most pressing problems and how you can use your career to solve them.","objects":{"entry":{"path":"content/templates_and_materials/80-000-hours-podcasts.md","sha":"9ea622b4fad105dc96ec633a87b9201b8204108f"},"files":[]},"timeStamp":"2018-11-12T20:59:48.706Z"}