{"type":"PR","pr":{"number":253,"head":"c6b2c4655d902771fd365872182f7e6933fc9198"},"user":"marcin.kowrygo","status":"pending_publish","branch":"cms/guide-to-depictin-poverty","collection":"guides_and_tips","title":"Guide To Depicting Poverty","description":"Representing poverty is a complex and controversial matter, and doing it in a sensitive and respectful manner is far from easy.","objects":{"entry":{"path":"content/guides_and_tips/guide-to-depictin-poverty.md","sha":"3e3967d6095085470beffbf0b5e4c05b71960ce8"},"files":[]},"timeStamp":"2018-11-27T20:14:47.696Z"}